AUTHORS
MANIFEST.in
README.rst
UNLICENSE.txt
pyproject.toml
setup.py
DynamicistToolKit.egg-info/PKG-INFO
DynamicistToolKit.egg-info/SOURCES.txt
DynamicistToolKit.egg-info/dependency_links.txt
DynamicistToolKit.egg-info/requires.txt
DynamicistToolKit.egg-info/top_level.txt
docs/Makefile
docs/conf.py
docs/dtk.rst
docs/index.rst
docs/make.bat
docs/references.rst
dtk/__init__.py
dtk/bicycle.py
dtk/control.py
dtk/inertia.py
dtk/process.py
dtk/version.py
dtk/test/__init__.py
dtk/test/test_bicycle.py
dtk/test/test_inertia.py
dtk/test/test_process.py
dtk/test/data/example_vertical_grf.csv