Metadata-Version: 2.4
Name: DynamicistToolKit
Version: 0.6.2
Summary: Various tools for theoretical and experimental dynamics.
Home-page: http://github.com/moorepants/DynamicistToolKit
Author: Jason K. Moore
Author-email: moorepants@gmail.com
License: UNLICENSE.txt
Classifier: Development Status :: 4 - Beta
Classifier: Intended Audience :: Science/Research
Classifier: Operating System :: OS Independent
Classifier: Programming Language :: Python :: 3.8
Classifier: Programming Language :: Python :: 3.9
Classifier: Programming Language :: Python :: 3.10
Classifier: Programming Language :: Python :: 3.11
Classifier: Programming Language :: Python :: 3.12
Classifier: Topic :: Scientific/Engineering :: Physics
License-File: AUTHORS
Requires-Dist: matplotlib>=3.5.1
Requires-Dist: numpy>=1.21.5
Requires-Dist: scipy>=1.8.0
Provides-Extra: doc
Requires-Dist: sphinx>=4.3.2; extra == "doc"
Requires-Dist: numpydoc>=1.2; extra == "doc"
Dynamic: author
Dynamic: author-email
Dynamic: classifier
Dynamic: description
Dynamic: home-page
Dynamic: license
Dynamic: license-file
Dynamic: provides-extra
Dynamic: requires-dist
Dynamic: summary
